narchi/__init__.py
narchi/blocks.py
narchi/graph.py
narchi/module.py
narchi/render.py
narchi/schemas.py
narchi/sympy.py
narchi/bin/__init__.py
narchi/bin/narchi_cli.py
narchi/instantiators/__init__.py
narchi/instantiators/common.py
narchi/instantiators/pytorch.py
narchi/instantiators/pytorch_packed.py
narchi/propagators/__init__.py
narchi/propagators/base.py
narchi/propagators/concat.py
narchi/propagators/conv.py
narchi/propagators/fixed.py
narchi/propagators/group.py
narchi/propagators/reshape.py
narchi/propagators/rnn.py
narchi/propagators/same.py
narchi_tests/__init__.py
narchi_tests/__main__.py
narchi_tests/cli_tests.py
narchi_tests/instantiators_tests.py
narchi_tests/module_tests.py
narchi_tests/propagators_tests.py
narchi_tests/schema_tests.py
narchi_tests/sympy_tests.py
narchi_tests/data/__init__.py
narchi_tests/data/imagenet_classifier.jsonnet
narchi_tests/data/laia.jsonnet
narchi_tests/data/nested1.jsonnet
narchi_tests/data/resnet.jsonnet
narchi_tests/data/resnet_multiscale.jsonnet
narchi_tests/data/squeezenet.jsonnet
narchi_tests/data/text_image_classification.jsonnet
narchi_tests/data/nested/nested3.jsonnet
narchi_tests/data/nested/nested/nested2.jsonnet
narchi-1.6.0.dist-info/LICENSE.rst
narchi-1.6.0.dist-info/METADATA
narchi-1.6.0.dist-info/WHEEL
narchi-1.6.0.dist-info/entry_points.txt
narchi-1.6.0.dist-info/top_level.txt
narchi-1.6.0.dist-info/RECORD
