Metadata-Version: 2.1
Name: narchi
Version: 1.6.0
Summary: A framework for defining, validating and visualizing neural network architectures.
Home-page: https://omni-us.github.io/narchi
Author: Mauricio Villegas
Author-email: mauricio@omnius.com
License: MIT
Project-URL: Documentation-stable, https://narchi.readthedocs.io/en/stable/
Project-URL: Documentation-latest, https://narchi.readthedocs.io/en/latest/
Project-URL: GitHub, https://github.com/omni-us/narchi
Project-URL: PyPI, https://pypi.org/project/narchi
Project-URL: CircleCI, https://circleci.com/gh/omni-us/narchi
Project-URL: SonarCloud, https://sonarcloud.io/dashboard?id=omni-us_narchi
Project-URL: Codecov, https://codecov.io/gh/omni-us/narchi
Platform: any
Classifier: Development Status :: 5 - Production/Stable
Classifier: Programming Language :: Python
Classifier: Programming Language :: Python :: 3
Classifier: Programming Language :: Python :: 3 :: Only
Classifier: Programming Language :: Python :: 3.6
Classifier: Programming Language :: Python :: 3.7
Classifier: Programming Language :: Python :: 3.8
Classifier: Programming Language :: Python :: 3.9
Classifier: Intended Audience :: Developers
Classifier: License :: OSI Approved :: MIT License
Classifier: Operating System :: POSIX :: Linux
Classifier: Operating System :: Unix
Classifier: Operating System :: MacOS
Requires-Python: >=3.6
License-File: LICENSE.rst
Requires-Dist: jsonargparse (>=3.0.1)
Requires-Dist: jsonschema (>=2.6.0)
Requires-Dist: jsonnet (>=0.13.0)
Requires-Dist: networkx (>=2.4)
Requires-Dist: sympy (>=1.4)
Provides-Extra: all
Requires-Dist: pygraphviz (>=1.5) ; extra == 'all'
Requires-Dist: torch (>=1.3.1) ; extra == 'all'
Requires-Dist: numpy (>=1.19.2) ; extra == 'all'
Provides-Extra: dev
Requires-Dist: pygraphviz (>=1.5) ; extra == 'dev'
Requires-Dist: torch (>=1.3.1) ; extra == 'dev'
Requires-Dist: numpy (>=1.19.2) ; extra == 'dev'
Requires-Dist: coverage (>=4.5.1) ; extra == 'dev'
Requires-Dist: pylint (>=1.8.3) ; extra == 'dev'
Requires-Dist: pycodestyle (>=2.5.0) ; extra == 'dev'
Requires-Dist: bump2version (>=0.5.11) ; extra == 'dev'
Requires-Dist: twine (>=3.1.1) ; extra == 'dev'
Provides-Extra: doc
Requires-Dist: Sphinx (>=1.7.9) ; extra == 'doc'
Requires-Dist: sphinx-rtd-theme (>=0.4.3) ; extra == 'doc'
Requires-Dist: sphinx-argparse (>=0.2.5) ; extra == 'doc'
Requires-Dist: autodocsumm (>=0.1.10) ; extra == 'doc'
Requires-Dist: sphinx-autodoc-typehints (>=1.11.1) ; extra == 'doc'
Requires-Dist: json-schema-for-humans (>=0.15.2) ; extra == 'doc'
Provides-Extra: pygraphviz
Requires-Dist: pygraphviz (>=1.5) ; extra == 'pygraphviz'
Provides-Extra: pytorch
Requires-Dist: torch (>=1.3.1) ; extra == 'pytorch'
Requires-Dist: numpy (>=1.19.2) ; extra == 'pytorch'
Provides-Extra: test
Requires-Dist: coverage (>=4.5.1) ; extra == 'test'
